README.md
setup.cfg
setup.py
DeepMAsED/Evaluate.py
DeepMAsED/Features.py
DeepMAsED/Models.py
DeepMAsED/Predict.py
DeepMAsED/Train.py
DeepMAsED/Utils.py
DeepMAsED/__init__.py
DeepMAsED/__main__.py
DeepMAsED.egg-info/PKG-INFO
DeepMAsED.egg-info/SOURCES.txt
DeepMAsED.egg-info/dependency_links.txt
DeepMAsED.egg-info/entry_points.txt
DeepMAsED.egg-info/requires.txt
DeepMAsED.egg-info/top_level.txt
DeepMAsED/Commands/Evaluate.py
DeepMAsED/Commands/Features.py
DeepMAsED/Commands/Predict.py
DeepMAsED/Commands/Train.py
DeepMAsED/Commands/__init__.py
DeepMAsED/Model/deepmased_mean_std.pkl
DeepMAsED/Model/deepmased_model.h5
tests/__init__.py
tests/test_Evaluate.py
tests/test_Features.py
tests/test_Predict.py
tests/test_Train.py