Metadata-Version: 1.0
Name: DeepMAsED
Version: 0.3.1
Summary: Deep learning for Metagenome Assembly Error Detection
Home-page: https://github.com/leylabmpi/DeepMAsED
Author: Nick Youngblut
Author-email: nyoungb2@gmail.com
License: MIT license
Platform: UNKNOWN
